ctrlengine/__init__.py
ctrlengine/ai/PoseEngine.py
ctrlengine/ai/__init__.py
ctrlengine/ai/azure_vision.py
ctrlengine/ai/cloud_vision.py
ctrlengine/ai/face_detection.py
ctrlengine/ai/image_classification.py
ctrlengine/ai/image_segmentation.py
ctrlengine/ai/object_detection.py
ctrlengine/ai/palm_detection.py
ctrlengine/ai/pose_detection.py
ctrlengine/ai/test.py
ctrlengine/ai/text_to_speech.py
ctrlengine/ai/dev/__init__.py
ctrlengine/ai/dev/face_recognition.py
ctrlengine/ai/dev/get_images.py
ctrlengine/ai/dev/verify.py
ctrlengine/controllers/__init__.py
ctrlengine/controllers/pid.py
ctrlengine/filters/__init__.py
ctrlengine/filters/ewma.py
ctrlengine/filters/exponentially_weighted_moving_average.py
ctrlengine/filters/simple_moving_average.py
ctrlengine/filters/sma.py
ctrlengine/interface/__init__.py
ctrlengine/interface/xbox.py
ctrlengine/sensors/__init__.py
ctrlengine/sensors/camera.py
ctrlengine/util/__init__.py
ctrlengine/util/logger.py
ctrlengine/util/reporter.py
ctrl.engine-0.0.3.dist-info/LICENSE
ctrl.engine-0.0.3.dist-info/METADATA
ctrl.engine-0.0.3.dist-info/WHEEL
ctrl.engine-0.0.3.dist-info/top_level.txt
ctrl.engine-0.0.3.dist-info/RECORD
