Metadata-Version: 2.1
Name: ctrl.engine
Version: 0.0.3
Summary: A universal control engine
Home-page: https://github.com/0xJeremy/ctrl.engine
Author: Jeremy Kanovsky
Author-email: kanovsky.jeremy@gmail.com
License: UNKNOWN
Platform: UNKNOWN
Classifier: Programming Language :: Python :: 3
Classifier: License :: OSI Approved :: MIT License
